odoo8_addon_product_profile-8.0.1.0.2.99.dev16-py2.7-nspkg.pth
odoo8_addon_product_profile-8.0.1.0.2.99.dev16.dist-info/DESCRIPTION.rst
odoo8_addon_product_profile-8.0.1.0.2.99.dev16.dist-info/METADATA
odoo8_addon_product_profile-8.0.1.0.2.99.dev16.dist-info/RECORD
odoo8_addon_product_profile-8.0.1.0.2.99.dev16.dist-info/WHEEL
odoo8_addon_product_profile-8.0.1.0.2.99.dev16.dist-info/metadata.json
odoo8_addon_product_profile-8.0.1.0.2.99.dev16.dist-info/namespace_packages.txt
odoo8_addon_product_profile-8.0.1.0.2.99.dev16.dist-info/top_level.txt
odoo_addons/product_profile/README.rst
odoo_addons/product_profile/__init__.py
odoo_addons/product_profile/__openerp__.py
odoo_addons/product_profile/config.py
odoo_addons/product_profile/config_view.xml
odoo_addons/product_profile/product.py
odoo_addons/product_profile/product_view.xml
odoo_addons/product_profile/demo/product.profile.csv
odoo_addons/product_profile/i18n/ca.po
odoo_addons/product_profile/i18n/de.po
odoo_addons/product_profile/i18n/es.po
odoo_addons/product_profile/i18n/fr.po
odoo_addons/product_profile/i18n/product_profile.pot
odoo_addons/product_profile/i18n/sl.po
odoo_addons/product_profile/security/group.xml
odoo_addons/product_profile/security/ir.model.access.csv
odoo_addons/product_profile/static/description/akretion.png
odoo_addons/product_profile/static/description/c1.png
odoo_addons/product_profile/static/description/c2.png
odoo_addons/product_profile/static/description/c3.png
odoo_addons/product_profile/static/description/field.png
odoo_addons/product_profile/static/description/icon.png
odoo_addons/product_profile/static/description/index.html
odoo_addons/product_profile/static/description/list.png
odoo_addons/product_profile/static/description/prof_warning.png
